{
	"info": {
		"_postman_id": "12345678-1234-1234-1234-123456789abc",
		"name": "Fonica API",
		"description": "API collection for testing Fonica NodeJS API endpoints",
		"schema": "https://schema.getpostman.com/json/collection/v2.1.0/collection.json"
	},
	"item": [
		{
			"name": "Auth",
			"item": [
				{
					"name": "Register Player",
					"request": {
						"method": "POST",
						"header": [
							{
								"key": "Content-Type",
								"value": "application/json"
							}
						],
						"body": {
							"mode": "raw",
							"raw": "{\n  \"name\": \"John Doe\",\n  \"email\": \"john@example.com\",\n  \"password\": \"password123\"\n}"
						},
						"url": {
							"raw": "{{base_url}}/api/auth/register",
							"host": ["{{base_url}}"],
							"path": ["api", "auth", "register"]
						}
					}
				},
				{
					"name": "Login Player",
					"request": {
						"method": "POST",
						"header": [
							{
								"key": "Content-Type",
								"value": "application/json"
							}
						],
						"body": {
							"mode": "raw",
							"raw": "{\n  \"email\": \"john@example.com\",\n  \"password\": \"password123\"\n}"
						},
						"url": {
							"raw": "{{base_url}}/api/auth/login",
							"host": ["{{base_url}}"],
							"path": ["api", "auth", "login"]
						}
					}
				},
				{
					"name": "Get Current User",
					"request": {
						"method": "GET",
						"header": [
							{
								"key": "Authorization",
								"value": "Bearer {{access_token}}"
							}
						],
						"url": {
							"raw": "{{base_url}}/api/auth/me",
							"host": ["{{base_url}}"],
							"path": ["api", "auth", "me"]
						}
					}
				},
				{
					"name": "Logout",
					"request": {
						"method": "POST",
						"header": [
							{
								"key": "Authorization",
								"value": "Bearer {{access_token}}"
							}
						],
						"url": {
							"raw": "{{base_url}}/api/auth/logout",
							"host": ["{{base_url}}"],
							"path": ["api", "auth", "logout"]
						}
					}
				}
			]
		},
		{
			"name": "Games",
			"item": [
				{
					"name": "Create Game",
					"request": {
						"method": "POST",
						"header": [
							{
								"key": "Content-Type",
								"value": "application/json"
							},
							{
								"key": "Authorization",
								"value": "Bearer {{access_token}}"
							}
						],
						"body": {
							"mode": "raw",
							"raw": "{\n  \"title\": \"Soccer Championship Final\",\n  \"date\": \"2025-09-15T18:00:00Z\",\n  \"location\": \"Central Stadium\",\n  \"description\": \"Final match of the championship\"\n}"
						},
						"url": {
							"raw": "{{base_url}}/api/games",
							"host": ["{{base_url}}"],
							"path": ["api", "games"]
						}
					}
				},
				{
					"name": "Get All Games",
					"request": {
						"method": "GET",
						"header": [
							{
								"key": "Authorization",
								"value": "Bearer {{access_token}}"
							}
						],
						"url": {
							"raw": "{{base_url}}/api/games",
							"host": ["{{base_url}}"],
							"path": ["api", "games"]
						}
					}
				},
				{
					"name": "Get Game by ID",
					"request": {
						"method": "GET",
						"header": [
							{
								"key": "Authorization",
								"value": "Bearer {{access_token}}"
							}
						],
						"url": {
							"raw": "{{base_url}}/api/games/{{game_id}}",
							"host": ["{{base_url}}"],
							"path": ["api", "games", "{{game_id}}"]
						}
					}
				},
				{
					"name": "Update Game",
					"request": {
						"method": "PATCH",
						"header": [
							{
								"key": "Content-Type",
								"value": "application/json"
							},
							{
								"key": "Authorization",
								"value": "Bearer {{access_token}}"
							}
						],
						"body": {
							"mode": "raw",
							"raw": "{\n  \"title\": \"Updated Game Title\",\n  \"location\": \"New Stadium\"\n}"
						},
						"url": {
							"raw": "{{base_url}}/api/games/{{game_id}}",
							"host": ["{{base_url}}"],
							"path": ["api", "games", "{{game_id}}"]
						}
					}
				},
				{
					"name": "Delete Game",
					"request": {
						"method": "DELETE",
						"header": [
							{
								"key": "Authorization",
								"value": "Bearer {{access_token}}"
							}
						],
						"url": {
							"raw": "{{base_url}}/api/games/{{game_id}}",
							"host": ["{{base_url}}"],
							"path": ["api", "games", "{{game_id}}"]
						}
					}
				},
				{
					"name": "Add Player to Game",
					"request": {
						"method": "POST",
						"header": [
							{
								"key": "Content-Type",
								"value": "application/json"
							},
							{
								"key": "Authorization",
								"value": "Bearer {{access_token}}"
							}
						],
						"body": {
							"mode": "raw",
							"raw": "{\n  \"playerId\": \"{{player_id}}\"\n}"
						},
						"url": {
							"raw": "{{base_url}}/api/games/{{game_id}}/players",
							"host": ["{{base_url}}"],
							"path": ["api", "games", "{{game_id}}", "players"]
						}
					}
				},
				{
					"name": "Add Multiple Players to Game",
					"request": {
						"method": "POST",
						"header": [
							{
								"key": "Content-Type",
								"value": "application/json"
							},
							{
								"key": "Authorization",
								"value": "Bearer {{access_token}}"
							}
						],
						"body": {
							"mode": "raw",
							"raw": "{\n  \"playerIds\": [\n    \"{{player_id_1}}\",\n    \"{{player_id_2}}\",\n    \"{{player_id_3}}\"\n  ]\n}"
						},
						"url": {
							"raw": "{{base_url}}/api/games/{{game_id}}/players/multiple",
							"host": ["{{base_url}}"],
							"path": ["api", "games", "{{game_id}}", "players", "multiple"]
						}
					}
				},
				{
					"name": "Update Player Status",
					"request": {
						"method": "PATCH",
						"header": [
							{
								"key": "Content-Type",
								"value": "application/json"
							},
							{
								"key": "Authorization",
								"value": "Bearer {{access_token}}"
							}
						],
						"body": {
							"mode": "raw",
							"raw": "{\n  \"status\": \"accepted\"\n}"
						},
						"url": {
							"raw": "{{base_url}}/api/games/{{game_id}}/players/{{player_id}}",
							"host": ["{{base_url}}"],
							"path": ["api", "games", "{{game_id}}", "players", "{{player_id}}"]
						}
					}
				}
			]
		},
		{
			"name": "Health Check",
			"request": {
				"method": "GET",
				"header": [],
				"url": {
					"raw": "{{base_url}}/health",
					"host": ["{{base_url}}"],
					"path": ["health"]
				}
			}
		}
	],
	"variable": [
		{
			"key": "base_url",
			"value": "http://localhost:3000",
			"type": "string"
		},
		{
			"key": "access_token",
			"value": "",
			"type": "string"
		},
		{
			"key": "game_id",
			"value": "",
			"type": "string"
		},
		{
			"key": "player_id",
			"value": "",
			"type": "string"
		},
		{
			"key": "player_id_1",
			"value": "",
			"type": "string"
		},
		{
			"key": "player_id_2",
			"value": "",
			"type": "string"
		},
		{
			"key": "player_id_3",
			"value": "",
			"type": "string"
		}
	]
}